pyday/__init__.py
pyday/pyday.py
daydotpy-0.0.1.dist-info/LICENSE
daydotpy-0.0.1.dist-info/METADATA
daydotpy-0.0.1.dist-info/WHEEL
daydotpy-0.0.1.dist-info/__init__.py
daydotpy-0.0.1.dist-info/pyday.py
daydotpy-0.0.1.dist-info/top_level.txt
daydotpy-0.0.1.dist-info/RECORD
